{
    "transcript": "大家好，这是《空食奔跑》评论，女士们，先生们，大家好 ，欢迎大家来到最新一期的《空 食奔跑》评论系列，我是本周报告的主持人，感谢您的入住，我不能’ 我 无法 抗拒，就介绍而言，呃，大力水手，我 从他们那里得到了一个新三明治，他们发布了一个新三明治，所以我有了三明治，但它装在这个绝对 巨大的袋子里，我决定玩点乐子到底为什么不，你 知道，我无法抗拒，因为我正在设置一切，我一看到它，我以为 我必须这样做，我不得不躲在它后面接受介绍，无论如何，波比有一个新的鸡肉 三明治出来了，好吧，我不知道它有多好，这就是我们要发现的，它被称为 金色烧烤鸡肉三明治，这就是它的名字，它是什么，这是一个非常 简单的三明治，呃，它带有他们的当然是他们的鸡胸肉， 上面有烧烤蜂蜜芥末酱，这就是这个新三明治的全部卖点，它还配有 泡菜，他们说三明治的目的是恢复午餐时间的兴奋，现在 不可否认，不一定是令人沮丧的 当你有 一个连锁店在谈论复兴某样东西 时，对我来说听起来从来都不是那么好， 所以你是在暗示，事情 并没有那么好，你必须复兴它，我不知道他们只是 最近 遇到了 很多问题，呃，人们对大力水手的热情和兴趣一直 在下降，质量很不稳定，我对大力水手的最后一次评论是 他们发布的一些翅膀，毫无疑问，他们是其中的一些我一生中吃过的最糟糕的鸡翅， 如果不是最糟糕的话，所以也许这里有一些东西需要复兴，我们会看到 金色的烧烤鸡肉三明治将成为催化剂，对吧，它会是呃，什么会 复兴午餐时间或我想就我而言，现在是晚餐时间，所以也许这并不适用，呃，兴奋， 无论如何，我们都会看到三明治，您可以将其作为普通三明治或作为膳食交易，我将其作为 普通三明治，只是一个三明治本身，它是有点贵，我不得不 承认 Popey's 的价格有点让我摇摇头，我确信它会 根据地区而有所不同，而且在你的情况下可能会有所不同，我买了这个三明治8 美元本身就是一个 8 美元的三明治，除此之外，因为你知道我不确定我是否会喜欢这个，所以 我想买另一件东西，你知道它就足够我的饭菜了，所以我继续 了我还买了一些鸡柳，呃，只有 5 个鸡柳，呃，只是一些薯条，价格是 20 美元，如果你问我的话，呃，这相当贵了，所以你知道这整顿饭几乎只是一个三明治 来回顾，然后呃投标，然后含税添加的所有东西都超过 30 美元， 所以你知道它就是这样，但价格不能说我是它们的忠实粉丝， 尽管如此，也许我会是三明治的忠实粉丝，它装在这个大袋子里，因为你可以 看到，然后那就是三明治实际上就在 那里，小袋限时优惠 我想我会 再次把它切成两半我不知道我 最近一直在享受横截面，我想最后一个我做的很受欢迎，所以 我们就非常俏皮，因为你可以看到直接，否则你知道 最大的吸引力是这种酱汁，这就是它 与其他任何东西的区别，你可以看到泡菜，鸡肉很多很多所以 如果我不能尝到基本的酱汁，我会感到震惊，否则我会拍一张 像那样的快速缩略图，也许我会再拍 一张，以防万一，黛布·邦宁（Deb Bunning）并不是 很多可看的东西 那里只有酱汁，所以现在我要做的就是把它切成两半我实际上要 在做这个的时候暂停相机，我还得把手洗干净，因为你可以看到酱汁我 什至还没有吃过它，我会给你一个快速的交叉横截面，然后 我们将进行评估，我会马上回来，正如你现在所看到的，横截面是 完成的看起来差不多，但你可以看到它看起来确实有很多鸡肉 ，我实际上把它倒过来，因为底部的面包不一定是水浸的， 但我猜酱汁是因为缺乏更好的词而记录的我实际上担心它的结构 完整性，但你看，这就是它的样子，现在让我们看看它的味道如何，让我们 看看它是否好吃，来自 Popey's 的金色烧烤鸡肉三明治，我 想只是为了厚颜无耻，我再咬一口，然后呃，就这样了， 所以 有趣的是，这个三明治的某些方面现在排在 第一位，也是最重要的，我认为它味道不错，这是主要的 收获，你知道它不是一个不好的项目或类似的东西，就这一点来说， 如果你只想知道最基本的，你知道最低限度，这篇 评论的最低限度味道就可以了，所以如果你只是想知道它是否好或者不在那里 ，但是关于这个项目有一些点是预期的，然后有 一些方面实际上让我有点惊讶，坦率地说，我喝了一口水， 你可能已经看到过这种情况像这样，你很可能自己经历过 很多次，你可能会看到，因为我的意思是这是一个简单的三明治， 这里没有太多成分，只有鸡肉、酱汁、面包和泡菜，这些 就是现在这里只有配料，你可以明显地看到，当我拿着这个，甚至 吃它时，三明治上有很多很多酱汁，事实上， 当我坐在这里时，你知道切三明治是这样的几乎就像一小 滩酱汁被挤出来，即便如此，你也知道有这么 多的酱汁，以至于它吸收了，因为他们显然非常慷慨，呃， 使用了烧烤蜂蜜芥末酱。顶部的面包甚至更多在底部的 面包上，它到处都是，可以理解的是，我现在在看这个的时候，你知道每一口都尝到它的味道吗， 因为你知道这是一个有趣的例子，酱汁 肯定 有一点香味 更有效的一面，所以你知道它闻起来像蜂蜜芥末酱，我有点 担心，我想这闻起来可能有点浓，而且 这个三明治上有这么多东西，所以它会太多吗你知道即使 它味道很好，它也会让人难以承受吗？咬一口，这很奇怪，你知道，我不 知道，也许我没有咬一口好，或者有什么东西，再咬一口，然后再咬一口， 尽管纯粹 是令人惊讶的，但还是很奇怪。 酱汁的量实际上并不是酱汁，尽管你会 认为这会非常有效，但酱汁实际上并不 比我预期的温和得多，这并不一定是A糟糕的是，上面有 太多的酱汁，我仍然可以很好地品尝它，我只是惊讶地发现，酱汁 没有它看起来那么浓，尤其是 现在有这么多的酱汁，而且质量也如此沙子的质量很好，因为真正谈论鸡肉的质量并不多， 我对鸡肉的质量很满意，因为你可以在 横截面中明显看到有大量的鸡肉，尽管你可以看到它很嫩我尴尬的 咬我并没有像你知道的那样啃东西，有时当我无聊时我会做什么我 在后院有这个呃轮胎就像这个旧汽车轮胎，呃我有时会出去然后 我会咬它，你知道，这不像我在外面做那样的事情，也不像 我啃掉你知道的东西，比如一块橡胶或其他你可以明显 看到鸡肉的东西嫩肉非常美味，质量很好，它不像通常那样酥脆，但 我显然可以看到这是因为三明治本身上有大量的酱汁， 你知道所有东西都吸收了鸡肉做的一点酱汁邦德做到了，所有这一切都是如此 不像平时那么脆，但味道还是不错，当然是快餐，但 鸡肉的质量很好，呃，这是一块质量很好的实心鸡肉，我对泡菜 和泡菜脆都很 满意 新鲜得体，大小我必须说，泡菜实际上很大 ，考虑到所有因素，当然，泡菜的锋利度总是与鸡肉 三明治相得益彰，这也不例外，所以基本成分都很好，面包就是面包， 没什么可说的。在这种情况下，也许勉强把它们结合在一起，但它确实 成功了，然后再次给我们留下了蜂蜜，烧烤蜂蜜芥末酱，现在它 效果很好，与鸡肉很好地融合在一起，我对它很满意，在这方面它有一个 正如人们对蜂蜜芥末酱的期望一样，它的锐度 很好 ，事实上，对我来说，这 比烧烤酱更容易被识别为蜂蜜芥末酱，所以你绝对可以尝到 蜂蜜芥末酱的味道，有一点点甜味当然，蜂蜜芥末 有一点点甜味，但它有很好的锐度，也 很好地赞美了鸡肉，它是一种很好的酱汁，综合考虑，所以就在那里，不错， 但最后我想说的是我想说的是，酱汁的效力不是 我所期望的，因为它有多少，而且闻起来像你知道的，它 只是不是我所看到的，它比我预想的要弱只是 我有点惊讶，我想这就是我想说的，让我调整这里的 一盏灯，快速保持，对这里的一盏灯感到抱歉，我不确定 它是否是只是光线的方式，或者如果只是我的话， 如果你看到我眯着眼睛，这会让我的眼睛有点困扰，这就是为什么我不得不稍微移动它，而且这也是 评论的结束所以这并不重要，但无论如何，我只是想说的是 ，你知道酱汁的效力或缺乏，这对我来说有点令人惊讶，因为当 那里有这么多酱汁时，当你只是想的时候它会比实际情况更坚固 ，我在这里唯一能想到的是，如果你碰巧拿到了这个三明治 ，假设你的教皇冰没有那么慷慨地应用了假设 我的酱汁当时可能会有点问题，因为 这个三明治上有太多酱汁，然后我好像可以尝一下，但如果酱汁少得多， 实际上可能很难完全辨别出这里的味道或者真正注意到它可能会 迷失在这里的其他味道中，所以酱汁有点淡，如果他们慷慨地 使用它，那么就不会有任何问题，它会造成一个混乱的三明治不过要小心 ，嗯，但是如果你的三明治上的东西少了，你就明白你可能无法品尝到 味道，我确实认为这是一个问题，像这样的酱汁 通常不应该像那样弱这是一个，它不一定需要浇上 酱汁，以便呃味道可以接受，并且能够真正注意到酱汁，所以这是一个 问题，而且它也有点贵，但所有有关的事情是它仍然是 就其本身而言，这是 一个不错的三明治， 所以呃，所以，十个三明治中，你知道这不是世界上最完美的三明治， 在我看来，酱汁可能会更浓一点，只要考虑到数量 与强度以及所有的因素虽然价格有点贵，但味道还是不错的 ，所以满分 10 分，我会给大力水手的金色烧烤鸡肉三明治打 7 分（满分 10 分），所以这就是它的评分今天，出于这篇评论中包含的所有原因， 这就是我对您的全部内容，再次对呃照明情况感到抱歉，只是 它只是分散了一点注意力，但最终一切都很好，如果您得到了 我的 沙子 我很好奇，如果您想知道酱汁对您的贡献如何，您可以发表评论 三明治是你的，酱汁和这个一样重，或者嗯，这是一种异常情况，我很好奇， 如果你碰巧也得到了这个三明治，你的大力水手是怎么做到的，这就是 我为你准备的一切，谢谢你的观看本周报告由我主持，敬请期待",
    "words": [
        {
            "startTime": 0.24,
            "endTime": 11.76,
            "word": "大家好，这是《空食奔跑》评论，女士们，先生们，大家好"
        },
        {
            "startTime": 11.76,
            "endTime": 15.84,
            "word": "，欢迎大家来到最新一期的《空"
        },
        {
            "startTime": 15.84,
            "endTime": 23.16,
            "word": "食奔跑》评论系列，我是本周报告的主持人，感谢您的入住，我不能’"
        },
        {
            "startTime": 15.84,
            "endTime": 23.16,
            "word": "我"
        },
        {
            "startTime": 15.84,
            "endTime": 23.16,
            "word": "无法"
        },
        {
            "startTime": 23.16,
            "endTime": 30.16,
            "word": "抗拒，就介绍而言，呃，大力水手，我"
        },
        {
            "startTime": 30.16,
            "endTime": 35.68,
            "word": "从他们那里得到了一个新三明治，他们发布了一个新三明治，所以我有了三明治，但它装在这个绝对"
        },
        {
            "startTime": 35.68,
            "endTime": 41.72,
            "word": "巨大的袋子里，我决定玩点乐子到底为什么不，你"
        },
        {
            "startTime": 41.72,
            "endTime": 46.76,
            "word": "知道，我无法抗拒，因为我正在设置一切，我一看到它，我以为"
        },
        {
            "startTime": 46.76,
            "endTime": 53.879999999999995,
            "word": "我必须这样做，我不得不躲在它后面接受介绍，无论如何，波比有一个新的鸡肉"
        },
        {
            "startTime": 53.88,
            "endTime": 60.36,
            "word": "三明治出来了，好吧，我不知道它有多好，这就是我们要发现的，它被称为"
        },
        {
            "startTime": 60.36,
            "endTime": 67.96,
            "word": "金色烧烤鸡肉三明治，这就是它的名字，它是什么，这是一个非常"
        },
        {
            "startTime": 67.96,
            "endTime": 74.72,
            "word": "简单的三明治，呃，它带有他们的当然是他们的鸡胸肉，"
        },
        {
            "startTime": 74.72,
            "endTime": 80.76,
            "word": "上面有烧烤蜂蜜芥末酱，这就是这个新三明治的全部卖点，它还配有"
        },
        {
            "startTime": 80.76,
            "endTime": 90.32000000000001,
            "word": "泡菜，他们说三明治的目的是恢复午餐时间的兴奋，现在"
        },
        {
            "startTime": 90.32,
            "endTime": 97.08,
            "word": "不可否认，不一定是令人沮丧的"
        },
        {
            "startTime": 90.32,
            "endTime": 97.08,
            "word": "当你有"
        },
        {
            "startTime": 90.32,
            "endTime": 97.08,
            "word": "一个连锁店在谈论复兴某样东西"
        },
        {
            "startTime": 97.08,
            "endTime": 101.96,
            "word": "时，对我来说听起来从来都不是那么好，"
        },
        {
            "startTime": 97.08,
            "endTime": 101.96,
            "word": "所以你是在暗示，事情"
        },
        {
            "startTime": 101.96,
            "endTime": 106.55999999999999,
            "word": "并没有那么好，你必须复兴它，我不知道他们只是"
        },
        {
            "startTime": 101.96,
            "endTime": 106.55999999999999,
            "word": "最近"
        },
        {
            "startTime": 101.96,
            "endTime": 106.55999999999999,
            "word": "遇到了"
        },
        {
            "startTime": 106.56,
            "endTime": 113.52,
            "word": "很多问题，呃，人们对大力水手的热情和兴趣一直"
        },
        {
            "startTime": 113.52,
            "endTime": 121.47999999999999,
            "word": "在下降，质量很不稳定，我对大力水手的最后一次评论是"
        },
        {
            "startTime": 121.48,
            "endTime": 127.80000000000001,
            "word": "他们发布的一些翅膀，毫无疑问，他们是其中的一些我一生中吃过的最糟糕的鸡翅，"
        },
        {
            "startTime": 127.8,
            "endTime": 134.0,
            "word": "如果不是最糟糕的话，所以也许这里有一些东西需要复兴，我们会看到"
        },
        {
            "startTime": 134.0,
            "endTime": 140.44,
            "word": "金色的烧烤鸡肉三明治将成为催化剂，对吧，它会是呃，什么会"
        },
        {
            "startTime": 140.44,
            "endTime": 147.64,
            "word": "复兴午餐时间或我想就我而言，现在是晚餐时间，所以也许这并不适用，呃，兴奋，"
        },
        {
            "startTime": 147.64,
            "endTime": 154.92,
            "word": "无论如何，我们都会看到三明治，您可以将其作为普通三明治或作为膳食交易，我将其作为"
        },
        {
            "startTime": 154.92,
            "endTime": 160.92,
            "word": "普通三明治，只是一个三明治本身，它是有点贵，我不得不"
        },
        {
            "startTime": 160.92,
            "endTime": 168.0,
            "word": "承认"
        },
        {
            "startTime": 160.92,
            "endTime": 168.0,
            "word": "Popey's"
        },
        {
            "startTime": 160.92,
            "endTime": 168.0,
            "word": "的价格有点让我摇摇头，我确信它会"
        },
        {
            "startTime": 168.0,
            "endTime": 175.04,
            "word": "根据地区而有所不同，而且在你的情况下可能会有所不同，我买了这个三明治8"
        },
        {
            "startTime": 168.0,
            "endTime": 175.04,
            "word": "美元本身就是一个"
        },
        {
            "startTime": 175.04,
            "endTime": 181.88,
            "word": "8"
        },
        {
            "startTime": 175.04,
            "endTime": 181.88,
            "word": "美元的三明治，除此之外，因为你知道我不确定我是否会喜欢这个，所以"
        },
        {
            "startTime": 181.88,
            "endTime": 187.04,
            "word": "我想买另一件东西，你知道它就足够我的饭菜了，所以我继续"
        },
        {
            "startTime": 187.04,
            "endTime": 195.12,
            "word": "了我还买了一些鸡柳，呃，只有"
        },
        {
            "startTime": 187.04,
            "endTime": 195.12,
            "word": "5"
        },
        {
            "startTime": 187.04,
            "endTime": 195.12,
            "word": "个鸡柳，呃，只是一些薯条，价格是"
        },
        {
            "startTime": 195.12,
            "endTime": 201.96,
            "word": "20"
        },
        {
            "startTime": 195.12,
            "endTime": 201.96,
            "word": "美元，如果你问我的话，呃，这相当贵了，所以你知道这整顿饭几乎只是一个三明治"
        },
        {
            "startTime": 201.96,
            "endTime": 210.0,
            "word": "来回顾，然后呃投标，然后含税添加的所有东西都超过"
        },
        {
            "startTime": 201.96,
            "endTime": 210.0,
            "word": "30"
        },
        {
            "startTime": 201.96,
            "endTime": 210.0,
            "word": "美元，"
        },
        {
            "startTime": 210.0,
            "endTime": 216.12,
            "word": "所以你知道它就是这样，但价格不能说我是它们的忠实粉丝，"
        },
        {
            "startTime": 216.12,
            "endTime": 221.84,
            "word": "尽管如此，也许我会是三明治的忠实粉丝，它装在这个大袋子里，因为你可以"
        },
        {
            "startTime": 221.84,
            "endTime": 231.64000000000001,
            "word": "看到，然后那就是三明治实际上就在"
        },
        {
            "startTime": 231.64,
            "endTime": 239.72,
            "word": "那里，小袋限时优惠"
        },
        {
            "startTime": 258.32,
            "endTime": 262.92,
            "word": "我想我会"
        },
        {
            "startTime": 262.92,
            "endTime": 268.44,
            "word": "再次把它切成两半我不知道我"
        },
        {
            "startTime": 268.44,
            "endTime": 272.88,
            "word": "最近一直在享受横截面，我想最后一个我做的很受欢迎，所以"
        },
        {
            "startTime": 272.88,
            "endTime": 287.4,
            "word": "我们就非常俏皮，因为你可以看到直接，否则你知道"
        },
        {
            "startTime": 287.4,
            "endTime": 292.32,
            "word": "最大的吸引力是这种酱汁，这就是它"
        },
        {
            "startTime": 292.32,
            "endTime": 299.84,
            "word": "与其他任何东西的区别，你可以看到泡菜，鸡肉很多很多所以"
        },
        {
            "startTime": 299.84,
            "endTime": 307.79999999999995,
            "word": "如果我不能尝到基本的酱汁，我会感到震惊，否则我会拍一张"
        },
        {
            "startTime": 307.8,
            "endTime": 316.56,
            "word": "像那样的快速缩略图，也许我会再拍"
        },
        {
            "startTime": 316.56,
            "endTime": 329.64,
            "word": "一张，以防万一，黛布·邦宁（Deb"
        },
        {
            "startTime": 316.56,
            "endTime": 329.64,
            "word": "Bunning）并不是"
        },
        {
            "startTime": 332.56,
            "endTime": 333.96,
            "word": "很多可看的东西"
        },
        {
            "startTime": 333.96,
            "endTime": 345.68,
            "word": "那里只有酱汁，所以现在我要做的就是把它切成两半我实际上要"
        },
        {
            "startTime": 345.68,
            "endTime": 351.24,
            "word": "在做这个的时候暂停相机，我还得把手洗干净，因为你可以看到酱汁我"
        },
        {
            "startTime": 351.24,
            "endTime": 357.12,
            "word": "什至还没有吃过它，我会给你一个快速的交叉横截面，然后"
        },
        {
            "startTime": 357.12,
            "endTime": 362.6,
            "word": "我们将进行评估，我会马上回来，正如你现在所看到的，横截面是"
        },
        {
            "startTime": 362.6,
            "endTime": 366.96000000000004,
            "word": "完成的看起来差不多，但你可以看到它看起来确实有很多鸡肉"
        },
        {
            "startTime": 366.96,
            "endTime": 373.12,
            "word": "，我实际上把它倒过来，因为底部的面包不一定是水浸的，"
        },
        {
            "startTime": 373.12,
            "endTime": 378.92,
            "word": "但我猜酱汁是因为缺乏更好的词而记录的我实际上担心它的结构"
        },
        {
            "startTime": 378.92,
            "endTime": 383.12,
            "word": "完整性，但你看，这就是它的样子，现在让我们看看它的味道如何，让我们"
        },
        {
            "startTime": 383.12,
            "endTime": 419.52,
            "word": "看看它是否好吃，来自"
        },
        {
            "startTime": 383.12,
            "endTime": 419.52,
            "word": "Popey's"
        },
        {
            "startTime": 383.12,
            "endTime": 419.52,
            "word": "的金色烧烤鸡肉三明治，我"
        },
        {
            "startTime": 445.32,
            "endTime": 451.92,
            "word": "想只是为了厚颜无耻，我再咬一口，然后呃，就这样了，"
        },
        {
            "startTime": 451.92,
            "endTime": 463.88,
            "word": "所以"
        },
        {
            "startTime": 463.88,
            "endTime": 472.24,
            "word": "有趣的是，这个三明治的某些方面现在排在"
        },
        {
            "startTime": 472.24,
            "endTime": 479.44,
            "word": "第一位，也是最重要的，我认为它味道不错，这是主要的"
        },
        {
            "startTime": 480.4,
            "endTime": 487.15999999999997,
            "word": "收获，你知道它不是一个不好的项目或类似的东西，就这一点来说，"
        },
        {
            "startTime": 487.16,
            "endTime": 493.32000000000005,
            "word": "如果你只想知道最基本的，你知道最低限度，这篇"
        },
        {
            "startTime": 493.32,
            "endTime": 499.24,
            "word": "评论的最低限度味道就可以了，所以如果你只是想知道它是否好或者不在那里"
        },
        {
            "startTime": 499.24,
            "endTime": 510.28000000000003,
            "word": "，但是关于这个项目有一些点是预期的，然后有"
        },
        {
            "startTime": 510.28,
            "endTime": 517.68,
            "word": "一些方面实际上让我有点惊讶，坦率地说，我喝了一口水，"
        },
        {
            "startTime": 517.68,
            "endTime": 531.0,
            "word": "你可能已经看到过这种情况像这样，你很可能自己经历过"
        },
        {
            "startTime": 531.0,
            "endTime": 538.6,
            "word": "很多次，你可能会看到，因为我的意思是这是一个简单的三明治，"
        },
        {
            "startTime": 538.6,
            "endTime": 546.0400000000001,
            "word": "这里没有太多成分，只有鸡肉、酱汁、面包和泡菜，这些"
        },
        {
            "startTime": 546.04,
            "endTime": 552.8399999999999,
            "word": "就是现在这里只有配料，你可以明显地看到，当我拿着这个，甚至"
        },
        {
            "startTime": 552.84,
            "endTime": 564.5600000000001,
            "word": "吃它时，三明治上有很多很多酱汁，事实上，"
        },
        {
            "startTime": 564.56,
            "endTime": 570.3199999999999,
            "word": "当我坐在这里时，你知道切三明治是这样的几乎就像一小"
        },
        {
            "startTime": 570.32,
            "endTime": 574.8000000000001,
            "word": "滩酱汁被挤出来，即便如此，你也知道有这么"
        },
        {
            "startTime": 574.8,
            "endTime": 581.12,
            "word": "多的酱汁，以至于它吸收了，因为他们显然非常慷慨，呃，"
        },
        {
            "startTime": 581.12,
            "endTime": 587.92,
            "word": "使用了烧烤蜂蜜芥末酱。顶部的面包甚至更多在底部的"
        },
        {
            "startTime": 587.92,
            "endTime": 595.8,
            "word": "面包上，它到处都是，可以理解的是，我现在在看这个的时候，你知道每一口都尝到它的味道吗，"
        },
        {
            "startTime": 595.8,
            "endTime": 602.92,
            "word": "因为你知道这是一个有趣的例子，酱汁"
        },
        {
            "startTime": 595.8,
            "endTime": 602.92,
            "word": "肯定"
        },
        {
            "startTime": 602.92,
            "endTime": 614.36,
            "word": "有一点香味"
        },
        {
            "startTime": 602.92,
            "endTime": 614.36,
            "word": "更有效的一面，所以你知道它闻起来像蜂蜜芥末酱，我有点"
        },
        {
            "startTime": 614.36,
            "endTime": 623.08,
            "word": "担心，我想这闻起来可能有点浓，而且"
        },
        {
            "startTime": 623.08,
            "endTime": 628.2,
            "word": "这个三明治上有这么多东西，所以它会太多吗你知道即使"
        },
        {
            "startTime": 628.2,
            "endTime": 635.0,
            "word": "它味道很好，它也会让人难以承受吗？咬一口，这很奇怪，你知道，我不"
        },
        {
            "startTime": 635.0,
            "endTime": 641.28,
            "word": "知道，也许我没有咬一口好，或者有什么东西，再咬一口，然后再咬一口，"
        },
        {
            "startTime": 641.28,
            "endTime": 647.72,
            "word": "尽管纯粹"
        },
        {
            "startTime": 641.28,
            "endTime": 647.72,
            "word": "是令人惊讶的，但还是很奇怪。"
        },
        {
            "startTime": 641.28,
            "endTime": 647.72,
            "word": "酱汁的量实际上并不是酱汁，尽管你会"
        },
        {
            "startTime": 647.72,
            "endTime": 653.32,
            "word": "认为这会非常有效，但酱汁实际上并不"
        },
        {
            "startTime": 653.32,
            "endTime": 661.2,
            "word": "比我预期的温和得多，这并不一定是A糟糕的是，上面有"
        },
        {
            "startTime": 661.2,
            "endTime": 667.84,
            "word": "太多的酱汁，我仍然可以很好地品尝它，我只是惊讶地发现，酱汁"
        },
        {
            "startTime": 667.84,
            "endTime": 675.12,
            "word": "没有它看起来那么浓，尤其是"
        },
        {
            "startTime": 675.12,
            "endTime": 682.36,
            "word": "现在有这么多的酱汁，而且质量也如此沙子的质量很好，因为真正谈论鸡肉的质量并不多，"
        },
        {
            "startTime": 682.36,
            "endTime": 689.32,
            "word": "我对鸡肉的质量很满意，因为你可以在"
        },
        {
            "startTime": 689.32,
            "endTime": 695.96,
            "word": "横截面中明显看到有大量的鸡肉，尽管你可以看到它很嫩我尴尬的"
        },
        {
            "startTime": 695.96,
            "endTime": 703.4000000000001,
            "word": "咬我并没有像你知道的那样啃东西，有时当我无聊时我会做什么我"
        },
        {
            "startTime": 703.4,
            "endTime": 710.16,
            "word": "在后院有这个呃轮胎就像这个旧汽车轮胎，呃我有时会出去然后"
        },
        {
            "startTime": 710.16,
            "endTime": 715.7199999999999,
            "word": "我会咬它，你知道，这不像我在外面做那样的事情，也不像"
        },
        {
            "startTime": 715.72,
            "endTime": 721.6800000000001,
            "word": "我啃掉你知道的东西，比如一块橡胶或其他你可以明显"
        },
        {
            "startTime": 721.68,
            "endTime": 731.92,
            "word": "看到鸡肉的东西嫩肉非常美味，质量很好，它不像通常那样酥脆，但"
        },
        {
            "startTime": 731.92,
            "endTime": 739.4,
            "word": "我显然可以看到这是因为三明治本身上有大量的酱汁，"
        },
        {
            "startTime": 739.4,
            "endTime": 748.28,
            "word": "你知道所有东西都吸收了鸡肉做的一点酱汁邦德做到了，所有这一切都是如此"
        },
        {
            "startTime": 748.28,
            "endTime": 755.28,
            "word": "不像平时那么脆，但味道还是不错，当然是快餐，但"
        },
        {
            "startTime": 755.28,
            "endTime": 763.28,
            "word": "鸡肉的质量很好，呃，这是一块质量很好的实心鸡肉，我对泡菜"
        },
        {
            "startTime": 763.28,
            "endTime": 771.56,
            "word": "和泡菜脆都很"
        },
        {
            "startTime": 763.28,
            "endTime": 771.56,
            "word": "满意"
        },
        {
            "startTime": 763.28,
            "endTime": 771.56,
            "word": "新鲜得体，大小我必须说，泡菜实际上很大"
        },
        {
            "startTime": 771.56,
            "endTime": 777.64,
            "word": "，考虑到所有因素，当然，泡菜的锋利度总是与鸡肉"
        },
        {
            "startTime": 777.64,
            "endTime": 783.88,
            "word": "三明治相得益彰，这也不例外，所以基本成分都很好，面包就是面包，"
        },
        {
            "startTime": 783.88,
            "endTime": 788.96,
            "word": "没什么可说的。在这种情况下，也许勉强把它们结合在一起，但它确实"
        },
        {
            "startTime": 788.96,
            "endTime": 797.84,
            "word": "成功了，然后再次给我们留下了蜂蜜，烧烤蜂蜜芥末酱，现在它"
        },
        {
            "startTime": 797.84,
            "endTime": 806.9200000000001,
            "word": "效果很好，与鸡肉很好地融合在一起，我对它很满意，在这方面它有一个"
        },
        {
            "startTime": 797.84,
            "endTime": 806.9200000000001,
            "word": "正如人们对蜂蜜芥末酱的期望一样，它的锐度"
        },
        {
            "startTime": 797.84,
            "endTime": 806.9200000000001,
            "word": "很好"
        },
        {
            "startTime": 806.92,
            "endTime": 812.68,
            "word": "，事实上，对我来说，这"
        },
        {
            "startTime": 812.68,
            "endTime": 821.28,
            "word": "比烧烤酱更容易被识别为蜂蜜芥末酱，所以你绝对可以尝到"
        },
        {
            "startTime": 821.28,
            "endTime": 827.76,
            "word": "蜂蜜芥末酱的味道，有一点点甜味当然，蜂蜜芥末"
        },
        {
            "startTime": 827.76,
            "endTime": 832.2,
            "word": "有一点点甜味，但它有很好的锐度，也"
        },
        {
            "startTime": 832.2,
            "endTime": 839.0400000000001,
            "word": "很好地赞美了鸡肉，它是一种很好的酱汁，综合考虑，所以就在那里，不错，"
        },
        {
            "startTime": 841.76,
            "endTime": 848.04,
            "word": "但最后我想说的是我想说的是，酱汁的效力不是"
        },
        {
            "startTime": 848.04,
            "endTime": 855.0799999999999,
            "word": "我所期望的，因为它有多少，而且闻起来像你知道的，它"
        },
        {
            "startTime": 855.08,
            "endTime": 862.2,
            "word": "只是不是我所看到的，它比我预想的要弱只是"
        },
        {
            "startTime": 862.2,
            "endTime": 870.44,
            "word": "我有点惊讶，我想这就是我想说的，让我调整这里的"
        },
        {
            "startTime": 870.44,
            "endTime": 876.84,
            "word": "一盏灯，快速保持，对这里的一盏灯感到抱歉，我不确定"
        },
        {
            "startTime": 876.84,
            "endTime": 880.84,
            "word": "它是否是只是光线的方式，或者如果只是我的话，"
        },
        {
            "startTime": 880.84,
            "endTime": 885.48,
            "word": "如果你看到我眯着眼睛，这会让我的眼睛有点困扰，这就是为什么我不得不稍微移动它，而且这也是"
        },
        {
            "startTime": 885.48,
            "endTime": 889.76,
            "word": "评论的结束所以这并不重要，但无论如何，我只是想说的是"
        },
        {
            "startTime": 889.76,
            "endTime": 894.76,
            "word": "，你知道酱汁的效力或缺乏，这对我来说有点令人惊讶，因为当"
        },
        {
            "startTime": 894.76,
            "endTime": 899.52,
            "word": "那里有这么多酱汁时，当你只是想的时候它会比实际情况更坚固"
        },
        {
            "startTime": 899.52,
            "endTime": 906.4,
            "word": "，我在这里唯一能想到的是，如果你碰巧拿到了这个三明治"
        },
        {
            "startTime": 906.4,
            "endTime": 912.56,
            "word": "，假设你的教皇冰没有那么慷慨地应用了假设"
        },
        {
            "startTime": 912.56,
            "endTime": 918.1199999999999,
            "word": "我的酱汁当时可能会有点问题，因为"
        },
        {
            "startTime": 918.12,
            "endTime": 925.36,
            "word": "这个三明治上有太多酱汁，然后我好像可以尝一下，但如果酱汁少得多，"
        },
        {
            "startTime": 925.36,
            "endTime": 930.96,
            "word": "实际上可能很难完全辨别出这里的味道或者真正注意到它可能会"
        },
        {
            "startTime": 930.96,
            "endTime": 937.48,
            "word": "迷失在这里的其他味道中，所以酱汁有点淡，如果他们慷慨地"
        },
        {
            "startTime": 937.48,
            "endTime": 942.2,
            "word": "使用它，那么就不会有任何问题，它会造成一个混乱的三明治不过要小心"
        },
        {
            "startTime": 942.2,
            "endTime": 948.5200000000001,
            "word": "，嗯，但是如果你的三明治上的东西少了，你就明白你可能无法品尝到"
        },
        {
            "startTime": 948.52,
            "endTime": 954.04,
            "word": "味道，我确实认为这是一个问题，像这样的酱汁"
        },
        {
            "startTime": 954.04,
            "endTime": 960.16,
            "word": "通常不应该像那样弱这是一个，它不一定需要浇上"
        },
        {
            "startTime": 960.16,
            "endTime": 968.04,
            "word": "酱汁，以便呃味道可以接受，并且能够真正注意到酱汁，所以这是一个"
        },
        {
            "startTime": 968.04,
            "endTime": 973.3199999999999,
            "word": "问题，而且它也有点贵，但所有有关的事情是它仍然是"
        },
        {
            "startTime": 968.04,
            "endTime": 973.3199999999999,
            "word": "就其本身而言，这是"
        },
        {
            "startTime": 968.04,
            "endTime": 973.3199999999999,
            "word": "一个不错的三明治，"
        },
        {
            "startTime": 973.32,
            "endTime": 979.12,
            "word": "所以呃，所以，十个三明治中，你知道这不是世界上最完美的三明治，"
        },
        {
            "startTime": 979.12,
            "endTime": 984.5600000000001,
            "word": "在我看来，酱汁可能会更浓一点，只要考虑到数量"
        },
        {
            "startTime": 984.56,
            "endTime": 988.64,
            "word": "与强度以及所有的因素虽然价格有点贵，但味道还是不错的"
        },
        {
            "startTime": 988.64,
            "endTime": 995.08,
            "word": "，所以满分"
        },
        {
            "startTime": 988.64,
            "endTime": 995.08,
            "word": "10"
        },
        {
            "startTime": 988.64,
            "endTime": 995.08,
            "word": "分，我会给大力水手的金色烧烤鸡肉三明治打"
        },
        {
            "startTime": 995.08,
            "endTime": 1001.96,
            "word": "7"
        },
        {
            "startTime": 995.08,
            "endTime": 1001.96,
            "word": "分（满分"
        },
        {
            "startTime": 995.08,
            "endTime": 1001.96,
            "word": "10"
        },
        {
            "startTime": 995.08,
            "endTime": 1001.96,
            "word": "分），所以这就是它的评分今天，出于这篇评论中包含的所有原因，"
        },
        {
            "startTime": 1001.96,
            "endTime": 1008.48,
            "word": "这就是我对您的全部内容，再次对呃照明情况感到抱歉，只是"
        },
        {
            "startTime": 1008.48,
            "endTime": 1014.5600000000001,
            "word": "它只是分散了一点注意力，但最终一切都很好，如果您得到了"
        },
        {
            "startTime": 1014.56,
            "endTime": 1019.8,
            "word": "我的"
        },
        {
            "startTime": 1014.56,
            "endTime": 1019.8,
            "word": "沙子"
        },
        {
            "startTime": 1014.56,
            "endTime": 1019.8,
            "word": "我很好奇，如果您想知道酱汁对您的贡献如何，您可以发表评论"
        },
        {
            "startTime": 1019.8,
            "endTime": 1026.6,
            "word": "三明治是你的，酱汁和这个一样重，或者嗯，这是一种异常情况，我很好奇，"
        },
        {
            "startTime": 1026.6,
            "endTime": 1032.3999999999999,
            "word": "如果你碰巧也得到了这个三明治，你的大力水手是怎么做到的，这就是"
        },
        {
            "startTime": 1032.4,
            "endTime": 1038.76,
            "word": "我为你准备的一切，谢谢你的观看本周报告由我主持，敬请期待"
        }
    ]
}